git_llm/__init__.py
git_llm/cli.py
git_llm/llm.py
git_llm/prompt.py
git_llm/utils/__init__.py
git_llm/utils/git.py
git_llm/utils/helpers.py
git_llm-0.1.3.dist-info/LICENSE
git_llm-0.1.3.dist-info/METADATA
git_llm-0.1.3.dist-info/WHEEL
git_llm-0.1.3.dist-info/entry_points.txt
git_llm-0.1.3.dist-info/RECORD
