Metadata-Version: 2.1
Name: git-llm
Version: 0.1.3
Summary: The project integrates Git with a llm (OpenAI, LlamaCpp, and GPT-4-All) to extend the capabilities of git.
Keywords: chatgpt,openai,cli
Author: Saryev Rustam
Author-email: rsaryev1997@gmail.com
Requires-Python: >=3.9,<4.0
Classifier: Programming Language :: Python :: 3
Classifier: Programming Language :: Python :: 3.9
Classifier: Programming Language :: Python :: 3.10
Classifier: Programming Language :: Python :: 3.11
Requires-Dist: fire (>=0.5.0,<0.6.0)
Requires-Dist: gitpython (>=3.1.31,<4.0.0)
Requires-Dist: gpt4all (>=0.2.3,<0.3.0)
Requires-Dist: halo (>=0.0.31,<0.0.32)
Requires-Dist: langchain (>=0.0.184,<0.0.185)
Requires-Dist: openai (>=0.27.7,<0.28.0)
Requires-Dist: questionary (>=1.10.0,<2.0.0)
Requires-Dist: tiktoken (>=0.4.0,<0.5.0)
Requires-Dist: torch (>=2.0.1,<3.0.0)
Requires-Dist: transformers (>=4.29.2,<5.0.0)
Requires-Dist: urllib3 (==1.26.6)
